django_orders_flavor-0.0.7.dist-info/DESCRIPTION.rst
django_orders_flavor-0.0.7.dist-info/METADATA
django_orders_flavor-0.0.7.dist-info/RECORD
django_orders_flavor-0.0.7.dist-info/WHEEL
django_orders_flavor-0.0.7.dist-info/metadata.json
django_orders_flavor-0.0.7.dist-info/top_level.txt
orders/__init__.py
orders/admin.py
orders/apps.py
orders/factories.py
orders/managers.py
orders/models.py
orders/settings.py
orders/shortcuts.py
orders/urls.py
orders/views.py
orders/api/__init__.py
orders/api/permissions.py
orders/api/serializers.py
orders/api/urls.py
orders/api/v1/__init__.py
orders/api/v1/urls.py
orders/api/v1/views.py
orders/migrations/0001_initial.py
orders/migrations/__init__.py
orders/signals/__init__.py
orders/signals/orders.py
orders/signals/paypal.py
