Metadata-Version: 2.0
Name: django-orders-flavor
Version: 0.0.7
Summary: Django app for orders
Home-page: https://github.com/flavors/orders/
Author: mongkok
Author-email: dani.pyc@gmail.com
License: MIT
Platform: UNKNOWN
Classifier: Development Status :: 1 - Planning
Classifier: Environment :: Web Environment
Classifier: Intended Audience :: Developers
Classifier: License :: OSI Approved :: MIT License
Classifier: Operating System :: OS Independent
Classifier: Programming Language :: Python
Classifier: Programming Language :: Python :: 3
Classifier: Programming Language :: Python :: 3.4
Classifier: Programming Language :: Python :: 3.5
Classifier: Programming Language :: Python :: 3.6
Classifier: Framework :: Django
Requires-Dist: Pillow (>=4.1.1)
Requires-Dist: django-core-flavor (>=0.0.21)
Requires-Dist: django-countries-flavor (>=0.0.7)
Requires-Dist: django-filter (>=1.0.2)
Requires-Dist: django-model-utils (>=3.0.0)
Requires-Dist: django-paypal (>=0.3.6)
Requires-Dist: django-polymorphic (>=1.2)
Requires-Dist: djangorestframework (>=3.6.3)
Requires-Dist: sorl-thumbnail (>=12.3)
